officely_web_scraper/__init__.py
officely_web_scraper/config.py
officely_web_scraper/scan.py
officely_web_scraper-1.0.0.data/scripts/officely-scraper
officely_web_scraper-1.0.0.dist-info/LICENSE
officely_web_scraper-1.0.0.dist-info/METADATA
officely_web_scraper-1.0.0.dist-info/WHEEL
officely_web_scraper-1.0.0.dist-info/entry_points.txt
officely_web_scraper-1.0.0.dist-info/top_level.txt
officely_web_scraper-1.0.0.dist-info/RECORD
