Metadata-Version: 2.1
Name: officely-web-scraper
Version: 1.0.0
Summary: A powerful, recursive URL-smart web scraping tool
Home-page: https://github.com/roynativ/officely-web-scraper
Author: Roy Nativ
Author-email: roy@officely.ai
Classifier: Development Status :: 3 - Alpha
Classifier: Intended Audience :: Developers
Classifier: License :: OSI Approved :: MIT License
Classifier: Operating System :: OS Independent
Classifier: Programming Language :: Python :: 3
Classifier: Programming Language :: Python :: 3.7
Classifier: Programming Language :: Python :: 3.8
Classifier: Programming Language :: Python :: 3.9
Requires-Python: >=3.7
License-File: LICENSE
Requires-Dist: aiohttp ==3.8.4
Requires-Dist: beautifulsoup4 ==4.10.0
Requires-Dist: requests ==2.26.0
Requires-Dist: chardet ==4.0.0
